airflow_e2e/__init__.py
airflow_e2e/__main__.py
airflow_e2e/constants.py
airflow_e2e/parser.py
airflow_e2e/printer.py
airflow_e2e/builder/__init__.py
airflow_e2e/builder/builder.py
airflow_e2e/composer/__init__.py
airflow_e2e/composer/airflow_core_services_composer.py
airflow_e2e/composer/airflow_seeder_service_composer.py
airflow_e2e/composer/composer.py
airflow_e2e/composer/constants.py
airflow_e2e/composer/e2e_test_runner_service_composer.py
airflow_e2e/composer/envrc_file.py
airflow_e2e/composer/envrc_file_writer.py
airflow_e2e/composer/extra_services_composer.py
airflow_e2e/composer/manual_e2e_test_runner_service_composer.py
airflow_e2e/composer/docker_compose_file/__init__.py
airflow_e2e/composer/docker_compose_file/base_docker_compose_yaml_file.py
airflow_e2e/composer/docker_compose_file/constants.py
airflow_e2e/composer/docker_compose_file/docker_compose_dev_yaml_file.py
airflow_e2e/composer/docker_compose_file/docker_compose_extras_yaml_file.py
airflow_e2e/composer/docker_compose_file/docker_compose_manual_testing_yaml_file.py
airflow_e2e/composer/docker_compose_file/docker_compose_tests_yaml_file.py
airflow_e2e/composer/docker_compose_file/docker_compose_yaml_file.py
airflow_e2e/composer/docker_compose_file/services/__init__.py
airflow_e2e/composer/docker_compose_file/services/airflow_postgresql_service.py
airflow_e2e/composer/docker_compose_file/services/airflow_redis_service.py
airflow_e2e/composer/docker_compose_file/services/airflow_scheduler_service.py
airflow_e2e/composer/docker_compose_file/services/airflow_seeder_service.py
airflow_e2e/composer/docker_compose_file/services/airflow_web_service.py
airflow_e2e/composer/docker_compose_file/services/airflow_worker_service.py
airflow_e2e/composer/docker_compose_file/services/base_service.py
airflow_e2e/composer/docker_compose_file/services/e2e_test_runner_service.py
airflow_e2e/composer/docker_compose_file/services/manual_e2e_test_runner_service.py
airflow_e2e-0.2.2.dist-info/LICENSE
airflow_e2e-0.2.2.dist-info/METADATA
airflow_e2e-0.2.2.dist-info/WHEEL
airflow_e2e-0.2.2.dist-info/entry_points.txt
airflow_e2e-0.2.2.dist-info/top_level.txt
airflow_e2e-0.2.2.dist-info/RECORD
