Metadata-Version: 2.1
Name: airflow-e2e
Version: 0.2.2
Summary: Create E2E test scripts for Airflow DAGs testing
Home-page: https://github.com/jw-ng/airflow-e2e
Author: Jun Wei, Ng
Author-email: ngjunwei.15@gmail.com
License: UNKNOWN
Platform: UNKNOWN
Classifier: License :: OSI Approved :: GNU General Public License v3 (GPLv3)
Classifier: Programming Language :: Python :: 3
Classifier: Programming Language :: Python :: 3.10
License-File: LICENSE
Requires-Dist: PyYAML (>=6.0)
